Metadata-Version: 2.4
Name: iflow-mcp_infinitimeless-claude-lmstudio-bridge
Version: 1.0.0
Summary: An MCP server that bridges Claude with local LLMs running in LM Studio
Author: infinitimeless
License: MIT
Project-URL: Homepage, https://github.com/infinitimeless/claude-lmstudio-bridge
Project-URL: Repository, https://github.com/infinitimeless/claude-lmstudio-bridge
Keywords: mcp,lmstudio,claude,llm
Classifier: Development Status :: 4 - Beta
Classifier: Intended Audience :: Developers
Classifier: Programming Language :: Python :: 3
Classifier: Programming Language :: Python :: 3.8
Classifier: Programming Language :: Python :: 3.9
Classifier: Programming Language :: Python :: 3.10
Classifier: Programming Language :: Python :: 3.11
Requires-Python: >=3.8
Requires-Dist: mcp[cli]>=0.1.0
Requires-Dist: httpx>=0.24.0
Requires-Dist: python-dotenv>=1.0.0
Provides-Extra: dev
Requires-Dist: pytest>=7.0.0; extra == "dev"
